segmentae/__init__.py
segmentae/anomaly_detection.py
segmentae/autoencoders/__init__.py
segmentae/autoencoders/batch_norm.py
segmentae/autoencoders/dense.py
segmentae/autoencoders/ensemble.py
segmentae/clusters/__init__.py
segmentae/clusters/clustering.py
segmentae/clusters/models.py
segmentae/clusters/registry.py
segmentae/core/__init__.py
segmentae/core/base.py
segmentae/core/constants.py
segmentae/core/exceptions.py
segmentae/core/types.py
segmentae/data_sources/__init__.py
segmentae/data_sources/examples.py
segmentae/metrics/__init__.py
segmentae/metrics/performance_metrics.py
segmentae/optimization/__init__.py
segmentae/optimization/optimizer.py
segmentae/pipeline/__init__.py
segmentae/pipeline/reconstruction.py
segmentae/pipeline/segmentae.py
segmentae/processing/__init__.py
segmentae/processing/preprocessing.py
segmentae/processing/simplifier.py
segmentae/utils/__init__.py
segmentae/utils/validation.py
segmentae-1.5.21.dist-info/licenses/LICENSE
segmentae-1.5.21.dist-info/METADATA
segmentae-1.5.21.dist-info/WHEEL
segmentae-1.5.21.dist-info/top_level.txt
segmentae-1.5.21.dist-info/RECORD
