Metadata-Version: 2.4
Name: segmentae
Version: 1.5.21
Summary: SegmentAE: A Python Library for Anomaly Detection Optimization
Home-page: https://github.com/TsLu1s/SegmentAE
Author: Luís Fernando da Silva Santos
Author-email: luisf_ssantos@hotmail.com
License: MIT
Keywords: pythondata science,machine learning,deep learning,neural networks,autoencoder,clustering,anomaly detection,novelty detectionfraud detection,data preprocessing
Classifier: Intended Audience :: Education
Classifier: Intended Audience :: Developers
Classifier: Intended Audience :: Science/Research
Classifier: Intended Audience :: Customer Service
Classifier: Intended Audience :: Financial and Insurance Industry
Classifier: Intended Audience :: Healthcare Industry
Classifier: Intended Audience :: Telecommunications Industry
Classifier: Topic :: Scientific/Engineering :: Artificial Intelligence
Classifier: Topic :: Scientific/Engineering :: Information Analysis
Classifier: Topic :: Scientific/Engineering :: Mathematics
Classifier: License :: OSI Approved :: MIT License
Classifier: Operating System :: OS Independent
Classifier: Programming Language :: Python :: 3.10
Classifier: Programming Language :: Python :: 3.11
License-File: LICENSE
Requires-Dist: pandas>=1.2.0
Requires-Dist: numpy>=1.19.5
Requires-Dist: atlantic==1.1.67
Requires-Dist: tensorflow>=2.10.0
Requires-Dist: ucimlrepo>=0.0.7
Requires-Dist: scipy>=1.11.4
Requires-Dist: pydantic==2.0.0
Requires-Dist: matplotlib==3.9.3
Dynamic: author
Dynamic: author-email
Dynamic: classifier
Dynamic: description
Dynamic: description-content-type
Dynamic: home-page
Dynamic: keywords
Dynamic: license
Dynamic: license-file
Dynamic: requires-dist
Dynamic: summary
